[
    {
        "id":  1,
        "name":  "Ngô Thị Lan",
        "phone":  "0940888805",
        "group_id":  null,
        "email":  "ngothilan@yahoo.com",
        "address":  "776 Tôn Đức Thắng, Q.1, Cần Thơ"
    },
    {
        "id":  2,
        "name":  "Lý Thế Việt",
        "phone":  "0996888873",
        "group_id":  3,
        "email":  "lythếviệt@hotmail.com",
        "address":  "401 Lê Duẩn, Q.3, TP.HCM"
    },
    {
        "id":  3,
        "name":  "Lâm Như Khanh",
        "phone":  "0984924022",
        "group_id":  3,
        "email":  "lamnhukhanh@email.com",
        "address":  "978 Hai Bà Trưng, Q.1, Nha Trang"
    },
    {
        "id":  4,
        "name":  "Chu Thu Tú",
        "phone":  "0950167123",
        "group_id":  null,
        "email":  "chuthutu@yahoo.com",
        "address":  "311 Lê Văn Sỹ, Q.Bình Thạnh, TP.HCM"
    },
    {
        "id":  5,
        "name":  "Vũ Thế Sơn",
        "phone":  "0959111531",
        "group_id":  1,
        "email":  "vuthếson@email.com",
        "address":  "358 Lê Văn Sỹ, Q.Tân Phú, Đà Nẵng"
    },
    {
        "id":  6,
        "name":  "Lê Thị Minh",
        "phone":  "0999421863",
        "group_id":  null,
        "email":  "lethiminh@hotmail.com",
        "address":  "613 Tôn Đức Thắng, Q.Phú Nhuận, Hà Nội"
    },
    {
        "id":  7,
        "name":  "Hoàng Văn Ơi",
        "phone":  "0922268267",
        "group_id":  2,
        "email":  "hoangvanoi@hotmail.com",
        "address":  "410 Phan Đăng Lưu, Q.1, Cần Thơ"
    },
    {
        "id":  8,
        "name":  "Vũ Bảo Đạt",
        "phone":  "0943417353",
        "group_id":  2,
        "email":  "vubaodat@gmail.com",
        "address":  "579 Lê Văn Sỹ, Thủ Đức, Đà Nẵng"
    },
    {
        "id":  9,
        "name":  "Chu Thị Khanh",
        "phone":  "0984962551",
        "group_id":  3,
        "email":  "chuthikhanh@gmail.com",
        "address":  "523 Pasteur, Q.Tân Phú, Đà Nẵng"
    },
    {
        "id":  10,
        "name":  "Lưu Bảo Uy",
        "phone":  "0928516759",
        "group_id":  null,
        "email":  "luubaouy@gmail.com",
        "address":  "934 Nguyễn Huệ, Q.5, Hà Nội"
    },
    {
        "id":  11,
        "name":  "Tô Thị Trung",
        "phone":  "0956658771",
        "group_id":  3,
        "email":  "tothitrung@email.com",
        "address":  "257 Võ Văn Tần, Q.3, Đà Nẵng"
    },
    {
        "id":  12,
        "name":  "Võ Thị Trung",
        "phone":  "0987505816",
        "group_id":  4,
        "email":  "vothitrung@yahoo.com",
        "address":  "177 Nguyễn Huệ, Q.3, Vũng Tàu"
    },
    {
        "id":  13,
        "name":  "Chu Bảo An",
        "phone":  "0983399086",
        "group_id":  2,
        "email":  "chubaoan@gmail.com",
        "address":  "521 Cách Mạng Tháng 8, Q.Tân Bình, Đà Nẵng"
    },
    {
        "id":  14,
        "name":  "Hồ Thu Tú",
        "phone":  "0958946495",
        "group_id":  4,
        "email":  "hồthutu@hotmail.com",
        "address":  "788 Trần Hưng Đạo, Q.1, Nha Trang"
    },
    {
        "id":  15,
        "name":  "Hoàng Hữu Nam",
        "phone":  "0935431124",
        "group_id":  null,
        "email":  "hoanghữunam@email.com",
        "address":  "469 Lê Lợi, Thủ Đức, Huế"
    },
    {
        "id":  16,
        "name":  "Trần Như Dũng",
        "phone":  "0925472825",
        "group_id":  1,
        "email":  "trầnnhudung@gmail.com",
        "address":  "914 Nguyễn Đình Chiểu, Q.3, Đà Nẵng"
    },
    {
        "id":  17,
        "name":  "Hà Thanh Tú",
        "phone":  "0958068000",
        "group_id":  4,
        "email":  "hathanhtu@email.com",
        "address":  "115 Nam Kỳ Khởi Nghĩa, Q.10, Huế"
    },
    {
        "id":  18,
        "name":  "Vũ Quốc Việt",
        "phone":  "0964604666",
        "group_id":  2,
        "email":  "vuquốcviệt@yahoo.com",
        "address":  "808 Nguyễn Huệ, Q.10, TP.HCM"
    },
    {
        "id":  19,
        "name":  "Ngô Công Ơi",
        "phone":  "0945786288",
        "group_id":  null,
        "email":  "ngocongoi@yahoo.com",
        "address":  "238 Lý Thường Kiệt, Q.Bình Thạnh, TP.HCM"
    },
    {
        "id":  20,
        "name":  "Mai Quốc Nam",
        "phone":  "0952574298",
        "group_id":  4,
        "email":  "maiquốcnam@email.com",
        "address":  "378 Phan Đăng Lưu, Q.10, Cần Thơ"
    },
    {
        "id":  21,
        "name":  "Phan Minh Phương",
        "phone":  "0928034820",
        "group_id":  null,
        "email":  "phanminhphuong@hotmail.com",
        "address":  "214 Trần Hưng Đạo, Q.Phú Nhuận, Đà Nẵng"
    },
    {
        "id":  22,
        "name":  "Hoàng Minh Vân",
        "phone":  "0942322707",
        "group_id":  4,
        "email":  "hoangminhvan@yahoo.com",
        "address":  "419 Phan Đăng Lưu, Q.5, Hà Nội"
    },
    {
        "id":  23,
        "name":  "Lê Như Ơi",
        "phone":  "0984431362",
        "group_id":  2,
        "email":  "lenhuoi@hotmail.com",
        "address":  "736 Yersin, Q.Phú Nhuận, Hà Nội"
    },
    {
        "id":  24,
        "name":  "Mai Đức Sơn",
        "phone":  "0939667199",
        "group_id":  3,
        "email":  "maidứcson@yahoo.com",
        "address":  "316 Phan Đăng Lưu, Q.5, Huế"
    },
    {
        "id":  25,
        "name":  "Đặng Thế Yến",
        "phone":  "0959622595",
        "group_id":  null,
        "email":  "dặngthếyến@email.com",
        "address":  "862 Tôn Đức Thắng, Q.Tân Phú, Nha Trang"
    },
    {
        "id":  26,
        "name":  "Võ Thị Xuân",
        "phone":  "0916466540",
        "group_id":  1,
        "email":  "vothixuan@yahoo.com",
        "address":  "398 Điện Biên Phủ, Thủ Đức, Đà Nẵng"
    },
    {
        "id":  27,
        "name":  "Đặng Tuấn Đạt",
        "phone":  "0982380270",
        "group_id":  null,
        "email":  "dặngtuấndat@hotmail.com",
        "address":  "810 Lê Lợi, Q.Phú Nhuận, Hà Nội"
    },
    {
        "id":  28,
        "name":  "Tô Thanh Sơn",
        "phone":  "0922765648",
        "group_id":  1,
        "email":  "tothanhson@email.com",
        "address":  "514 Lê Lợi, Q.Bình Thạnh, TP.HCM"
    },
    {
        "id":  29,
        "name":  "Nguyễn Công Đạt",
        "phone":  "0997078711",
        "group_id":  1,
        "email":  "nguyễncongdat@email.com",
        "address":  "13 Cách Mạng Tháng 8, Q.3, Huế"
    },
    {
        "id":  30,
        "name":  "Đinh Bảo Dũng",
        "phone":  "0921561476",
        "group_id":  3,
        "email":  "dinhbaodung@yahoo.com",
        "address":  "66 Lê Duẩn, Q.Bình Thạnh, TP.HCM"
    },
    {
        "id":  31,
        "name":  "Dương Thế Nam",
        "phone":  "0934061168",
        "group_id":  null,
        "email":  "duongthếnam@email.com",
        "address":  "609 Nguyễn Huệ, Q.10, Cần Thơ"
    }
]
